{
  "collectionName": "components_shared_industries_views",
  "info": {
    "displayName": "Industries-View",
    "icon": "book",
    "description": ""
  },
  "options": {},
  "attributes": {
    "Title": {
      "type": "string"
    },
    "Description": {
      "type": "text"
    },
    "Button": {
      "type": "string"
    },
    "Image": {
      "type": "media",
      "multiple": false,
      "required": false,
      "allowedTypes": [
        "images",
        "files",
        "videos",
        "audios"
      ]
    }
  }
}
