{
  "collectionName": "components_shared_tech_categories",
  "info": {
    "displayName": "Tech-Categories",
    "icon": "grid",
    "description": ""
  },
  "options": {},
  "attributes": {
    "Categories": {
      "type": "string"
    },
    "Image1": {
      "type": "media",
      "multiple": false,
      "required": false,
      "allowedTypes": [
        "images",
        "files",
        "videos",
        "audios"
      ]
    },
    "Language1": {
      "type": "string"
    },
    "Image2": {
      "type": "media",
      "multiple": false,
      "required": false,
      "allowedTypes": [
        "images",
        "files",
        "videos",
        "audios"
      ]
    },
    "Language2": {
      "type": "string"
    },
    "Image3": {
      "type": "media",
      "multiple": false,
      "required": false,
      "allowedTypes": [
        "images",
        "files",
        "videos",
        "audios"
      ]
    },
    "Language3": {
      "type": "string"
    },
    "Image4": {
      "type": "media",
      "multiple": false,
      "required": false,
      "allowedTypes": [
        "images",
        "files",
        "videos",
        "audios"
      ]
    },
    "Language4": {
      "type": "string"
    },
    "Image5": {
      "type": "media",
      "multiple": false,
      "required": false,
      "allowedTypes": [
        "images",
        "files",
        "videos",
        "audios"
      ]
    },
    "Language5": {
      "type": "string"
    },
    "Image6": {
      "type": "media",
      "multiple": false,
      "required": false,
      "allowedTypes": [
        "images",
        "files",
        "videos",
        "audios"
      ]
    },
    "Language6": {
      "type": "string"
    }
  }
}
